formen/__init__.py
formen/main.py
formen-0.1.0.dist-info/METADATA
formen-0.1.0.dist-info/WHEEL
formen-0.1.0.dist-info/RECORD
