Metadata-Version: 2.1
Name: formen
Version: 0.1.0
Summary: 
Author: Türkalp Burak Kayrancıoğlu
Author-email: bkayranci@gmail.com
Requires-Python: >=3.11,<4.0
Classifier: Programming Language :: Python :: 3
Classifier: Programming Language :: Python :: 3.11
Requires-Dist: fastapi (>=0.103.1,<0.104.0)
Requires-Dist: uvicorn (>=0.23.2,<0.24.0)
